cpgen/__init__.py
cpgen/basic.py
cpgen/graph.py
cpgen-0.0.2.dist-info/LICENSE
cpgen-0.0.2.dist-info/METADATA
cpgen-0.0.2.dist-info/WHEEL
cpgen-0.0.2.dist-info/top_level.txt
cpgen-0.0.2.dist-info/RECORD
