Metadata-Version: 2.1
Name: cpgen
Version: 0.0.2
Summary: Random test-cases generator for competitive programming
Home-page: https://gitlab.com/finn02/generator
Author: Vipul Kumar
Author-email: finn98@protonmail.com
License: UNKNOWN
Platform: UNKNOWN
Classifier: Programming Language :: Python :: 3
Classifier: License :: OSI Approved :: MIT License
Classifier: Operating System :: OS Independent
